[
  {
    "id": 1,
    "video": "hook-01.mp4",
    "video_music": "hook-01-music.mp4",
    "caption": "The market's average annual return over the last 50 years is about 10%. You don't need to time it or beat it \u2014 you need to be in it, consistently, for a long time.",
    "hashtags": [
      "#investing",
      "#investing101",
      "#wealthbuilding",
      "#compoundinterest",
      "#financialliteracy"
    ],
    "based_on_format": "one-word aspirational template (needm_rari-style)",
    "platform_targets": [
      "tiktok",
      "instagram_reels",
      "youtube_shorts"
    ]
  },
  {
    "id": 2,
    "video": "hook-02.mp4",
    "video_music": "hook-02-music.mp4",
    "caption": "Old money isn't about the amount \u2014 it's about time in the market. A modest amount invested young and left alone for 30+ years usually beats a much larger amount invested late.",
    "hashtags": [
      "#wealthbuilding",
      "#oldmoney",
      "#investing101",
      "#compoundinterest",
      "#financialfreedom"
    ],
    "based_on_format": "aspirational two-word template (needm_rari-style)",
    "platform_targets": [
      "tiktok",
      "instagram_reels",
      "youtube_shorts"
    ]
  },
  {
    "id": 7,
    "video": "hook-07.mp4",
    "video_music": "hook-07-music.mp4",
    "caption": "A 750 credit score at 19 isn't luck. It's one card, paid off in full, every single month, for two years straight, with utilization under 10%. Payment history alone is 35% of the score. Start now and the number takes care of itself.",
    "hashtags": [
      "#creditscore",
      "#creditbuilding",
      "#financialliteracy",
      "#investing",
      "#moneytips"
    ],
    "based_on_format": "cinematic aesthetic edit (riskanddreward-style)",
    "platform_targets": [
      "tiktok",
      "instagram_reels",
      "youtube_shorts"
    ]
  },
  {
    "id": 8,
    "video": "hook-08.mp4",
    "video_music": "hook-08-music.mp4",
    "caption": "An emergency fund isn't exciting, but 3 months of essential expenses sitting in a high-yield savings account is the difference between a flat tire being an inconvenience and it being a crisis. Start with $500. Build from there.",
    "hashtags": [
      "#emergencyfund",
      "#savingsaccount",
      "#financialliteracy",
      "#investing",
      "#moneytips"
    ],
    "based_on_format": "cinematic aesthetic edit (riskanddreward-style)",
    "platform_targets": [
      "tiktok",
      "instagram_reels",
      "youtube_shorts"
    ]
  }
]