[
  {
    "id": 1,
    "images": [
      "01/01.png",
      "01/02.png",
      "01/03.png",
      "01/04.png",
      "01/05.png",
      "01/06.png",
      "01/07.png",
      "01/08.png",
      "01/09.png"
    ],
    "caption": "accidentally left my notes app open \ud83d\ude2c number 4 is gonna make people mad\n\nsave this before your next impulse buy.\n\nfree lessons + $100k practice money at mrguyinvests.com, link in bio \ud83d\udd79\ufe0f\n\n#moneytok #brokegirltips #financetok #adulting #fyp"
  },
  {
    "id": 2,
    "images": [
      "02/01.png",
      "02/02.png",
      "02/03.png",
      "02/04.png",
      "02/05.png",
      "02/06.png"
    ],
    "caption": "he left me on read but he'll thank me at 25 \ud83d\udc80 tag your little sibling\n\nmrguyinvests.com \u2014 learn money like a game, link in bio\n\n#moneytok #genz #brokecollegestudent #financetok #siblings #fyp"
  },
  {
    "id": 3,
    "images": [
      "03/01.png",
      "03/02.png",
      "03/03.png",
      "03/04.png",
      "03/05.png",
      "03/06.png",
      "03/07.png"
    ],
    "caption": "your savings account is robbing you and here's the math your bank prays you never do\n\ndefend your bank in the comments \ud83e\udd1a\n\n#moneytok #savings #hysa #financetok #banks #fyp"
  },
  {
    "id": 4,
    "images": [
      "04/01.png",
      "04/02.png",
      "04/03.png",
      "04/04.png",
      "04/05.png",
      "04/06.png"
    ],
    "caption": "found the realest money advice on the internet in a reddit thread \ud83d\udc80\n\nthe top comments are better than most finance classes\n\n#moneytok #college #brokecollegestudent #reddit #fyp"
  },
  {
    "id": 5,
    "images": [
      "05/01.png",
      "05/02.png",
      "05/03.png",
      "05/04.png",
      "05/05.png"
    ],
    "caption": "the community note on this finance guru is BRUTAL \ud83d\ude2d\n\n63% of stock advice on this app is misleading \u2014 always check who's selling what\n\n#fintok #moneytok #scam #communitynotes #fyp"
  },
  {
    "id": 6,
    "images": [
      "06/01.png",
      "06/02.png",
      "06/03.png",
      "06/04.png",
      "06/05.png",
      "06/06.png"
    ],
    "caption": "your money wrapped just dropped and it's NOT looking good bestie \ud83d\udc80\n\ndrop your most embarrassing stat below\n\n#wrapped #moneytok #doordash #brokegirl #fyp"
  },
  {
    "id": 7,
    "images": [
      "07/01.png",
      "07/02.png",
      "07/03.png",
      "07/04.png",
      "07/05.png"
    ],
    "caption": "which lock screen is yours? be honest \ud83d\udcf1\n\nslide 4 took 5 weeks and one uncomfortable conversation with myself\n\n#moneytok #doomspending #genz #fyp"
  },
  {
    "id": 8,
    "images": [
      "08/01.png",
      "08/02.png",
      "08/03.png",
      "08/04.png",
      "08/05.png",
      "08/06.png"
    ],
    "caption": "we've all searched 'why am i always broke' at 2am. here's every real answer \ud83d\udd0d\n\nthe doordash math hurt me too\n\n#moneytok #broke #genz #adulting #fyp"
  },
  {
    "id": 9,
    "images": [
      "09/01.png",
      "09/02.png",
      "09/03.png",
      "09/04.png",
      "09/05.png"
    ],
    "caption": "asked for the receipt on 'looking rich' and the cashier printed THIS \ud83e\uddfe\n\ncompliments per dollar: $412.80. that should be illegal.\n\n#moneytok #carpayment #genz #financetok #fyp"
  },
  {
    "id": 10,
    "images": [
      "10/01.png",
      "10/02.png",
      "10/03.png",
      "10/04.png",
      "10/05.png",
      "10/06.png"
    ],
    "caption": "ranked every student side hustle so you don't waste your summer \ud83c\udfc6\n\ndefend dropshipping in the comments, i'll wait (it's F tier)\n\n#sidehustle #studentjobs #moneytok #tierlist #fyp"
  },
  {
    "id": 11,
    "images": [
      "11/01.png",
      "11/02.png",
      "11/03.png",
      "11/04.png"
    ],
    "caption": "tag someone rocking the FULL starter pack \ud83d\udc80\n\npack #2 is learnable \u2014 that's the whole point\n\n#starterpack #moneytok #genz #broketok #fyp"
  },
  {
    "id": 12,
    "images": [
      "12/01.png",
      "12/02.png",
      "12/03.png",
      "12/04.png",
      "12/05.png",
      "12/06.png"
    ],
    "caption": "4 questions. no calculator. drop your score below (be honest) \ud83e\udde0\n\nQ3 is the most expensive myth in america\n\n#moneyquiz #financetok #creditscore #moneytok #fyp"
  },
  {
    "id": 13,
    "images": [
      "13/01.png",
      "13/02.png",
      "13/03.png",
      "13/04.png",
      "13/05.png"
    ],
    "caption": "the local scholarship cheat code nobody's counselor mentions \ud83c\udf93\n\nlower applicants, way better odds\n\n#scholarships #collegemoney #classof2027 #financialaid #fyp"
  },
  {
    "id": 14,
    "images": [
      "14/01.png",
      "14/02.png",
      "14/03.png",
      "14/04.png",
      "14/05.png",
      "14/06.png"
    ],
    "caption": "reading your transaction history out loud should be a crime \ud83d\udc80\n\nthe overdraft fee for having $0 is still the wildest thing banks do\n\n#moneytok #bankaccount #genz #financetok #fyp"
  },
  {
    "id": 15,
    "images": [
      "15/01.png",
      "15/02.png",
      "15/03.png",
      "15/04.png",
      "15/05.png"
    ],
    "caption": "POV: the gc plans cabo and one friend says the forbidden sentence \ud83c\udfdd\ufe0f\n\n'i can't, i'm broke' is a complete sentence \u2014 42% of gen z agrees\n\n#loudbudgeting #groupchat #springbreak #moneytok #fyp"
  },
  {
    "id": 16,
    "images": [
      "16/01.png",
      "16/02.png",
      "16/03.png",
      "16/04.png",
      "16/05.png"
    ],
    "caption": "apple needs to add this feature immediately \ud83d\udcf1\n\nopened bank app 2x. opened doordash 23x. the math is mathing.\n\n#screentime #moneytok #doordash #genz #fyp"
  },
  {
    "id": 17,
    "images": [
      "17/01.png",
      "17/02.png",
      "17/03.png",
      "17/04.png",
      "17/05.png",
      "17/06.png"
    ],
    "caption": "your money habits made dating profiles and half are red flags \ud83d\udea9\n\ncompound interest is 97 and still the most eligible bachelor on here\n\n#redflag #greenflag #datingapp #moneytok #fyp"
  },
  {
    "id": 18,
    "images": [
      "18/01.png",
      "18/02.png",
      "18/03.png",
      "18/04.png",
      "18/05.png"
    ],
    "caption": "Broke: Season 7. critically acclaimed. somehow renewed \ud83d\udc80\n\ncomment what you're binging. i was on doordash diaries s12\n\n#netflix #moneytok #broke #genz #fyp"
  },
  {
    "id": 19,
    "images": [
      "19/01.png",
      "19/02.png",
      "19/03.png",
      "19/04.png",
      "19/05.png"
    ],
    "caption": "the GPS route to $10k nobody gives you \ud83d\uddfa\ufe0f\n\nthe tolls on slide 3 double your trip time. avoid at all costs.\n\n#first10k #savings #roadtrip #moneytok #fyp"
  },
  {
    "id": 20,
    "images": [
      "20/01.png",
      "20/02.png",
      "20/03.png",
      "20/04.png",
      "20/05.png"
    ],
    "caption": "your wallet has a forecast and there's a severe alert \u26c8\ufe0f\n\nspending is weather. investing is climate. read that again.\n\n#weather #moneytok #doomspending #genz #fyp"
  },
  {
    "id": 21,
    "images": [
      "21/01.png",
      "21/02.png",
      "21/03.png",
      "21/04.png",
      "21/05.png"
    ],
    "caption": "the app store page for Being Broke is too accurate \ud83d\udcf1\n\ncomment your longest streak. mine was 17 years.\n\n#appstore #broke #moneytok #genz #fyp"
  },
  {
    "id": 22,
    "images": [
      "22/01.png",
      "22/02.png",
      "22/03.png",
      "22/04.png",
      "22/05.png"
    ],
    "caption": "i read my venmo feed like a crime scene. the findings are damning \ud83d\udd0d\n\nthe most important payment this week has zero likes\n\n#venmo #moneytok #genz #spendinghabits #fyp"
  },
  {
    "id": 23,
    "images": [
      "23/01.png",
      "23/02.png",
      "23/03.png",
      "23/04.png",
      "23/05.png"
    ],
    "caption": "the 30-day challenge that funds your first investment \ud83c\udfc6 save this\n\nnormal life is fine. this only kills autopilot spending. who's in for the 1st?\n\n#nospendchallenge #savingschallenge #nobuy2026 #moneychallenge #fyp"
  },
  {
    "id": 24,
    "images": [
      "24/01.png",
      "24/02.png",
      "24/03.png",
      "24/04.png",
      "24/05.png",
      "24/06.png"
    ],
    "caption": "the '$10k by 18' people are selling you something. here are the real numbers \ud83e\uddee\n\ndrop your age below, i'll reply with the one move for exactly where you are \ud83d\udc47\n\n#moneytok #genz #savings #brokestudent #fyp"
  },
  {
    "id": 25,
    "images": [
      "25/01.png",
      "25/02.png",
      "25/03.png",
      "25/04.png",
      "25/05.png",
      "25/06.png"
    ],
    "caption": "fact-checked my dad's money advice with love and receipts \u2764\ufe0f\ud83d\udce0\n\ncomment the wildest money advice your parents ever gave you\n\n#moneytok #parents #genz #creditscore #fyp"
  },
  {
    "id": 26,
    "images": [
      "26/01.png",
      "26/02.png",
      "26/03.png",
      "26/04.png",
      "26/05.png",
      "26/06.png"
    ],
    "caption": "your first paycheck is smaller than you calculated. here's exactly who took it \ud83e\uddfe\n\nthe january filing thing is real \u2014 ask me anything below\n\n#firstjob #paycheck #summerjob #moneytok #taxes #fyp"
  }
]